<?xml version="1.0" encoding="UTF-8"?>
<con:soapui-project id="5aadb37c-8da7-4923-bfd0-ab0168f2c7e4" activeEnvironment="Default" name="REST Project 1" resourceRoot="" soapui-version="5.2.1" abortOnError="false" runType="SEQUENTIAL" xmlns:con="http://eviware.com/soapui/config"><con:settings/><con:interface xsi:type="con:RestService" id="e374bf6c-116f-4893-aaa0-a6609fac7cef" wadlVersion="http://wadl.dev.java.net/2009/02" name="http://debian-vbox" type="rest" xmlns:xsi="http://www.w3.org/2001/XMLSchema-instance"><con:settings/><con:definitionCache type="TEXT" rootPart=""/><con:endpoints><con:endpoint>http://dev.bankidapp.xyz/</con:endpoint></con:endpoints><con:resource name="loggInnAdmin.php" path="/API/loggInnAdmin.php" id="81cb1f92-71bb-4e03-b926-e35b215e649d"><con:settings/><con:parameters><con:parameter><con:name>bruker</con:name><con:value/><con:style>QUERY</con:style><con:default/><con:description xsi:nil="true"/></con:parameter><con:parameter><con:name>passord</con:name><con:value/><con:style>QUERY</con:style><con:default/><con:description xsi:nil="true"/></con:parameter></con:parameters><con:method name="" id="fc14d04b-ef61-4188-b313-a8f4ae39ac4c" method="GET"><con:settings/><con:parameters/><con:representation type="RESPONSE"><con:mediaType>application/json</con:mediaType><con:status>200</con:status><con:params/></con:representation><con:request name="Request 1" id="4d77e73e-2481-41ec-b1f1-26e99fb36bbd" mediaType="application/json"><con:settings><con:setting id="com.eviware.soapui.impl.wsdl.WsdlRequest@request-headers">&lt;xml-fragment/></con:setting></con:settings><con:endpoint>http://debian-vbox/nettbank/public/</con:endpoint><con:request/><con:originalUri>http://debian-vbox/nettbank/public/API/hentAlleKunder.php</con:originalUri><con:credentials><con:authType>No Authorization</con:authType></con:credentials><con:jmsConfig JMSDeliveryMode="PERSISTENT"/><con:jmsPropertyConfig/><con:parameters>
  <con:entry key="passord" value="Admin"/>
  <con:entry key="bruker" value="Admin"/>
</con:parameters><con:parameterOrder><con:entry>bruker</con:entry><con:entry>passord</con:entry></con:parameterOrder></con:request></con:method></con:resource><con:resource name="hentAlleKunder.php" path="/API/hentAlleKunder.php" id="480c62d7-0f84-413e-8728-f6ac7741c670"><con:settings/><con:parameters/><con:method name="Method 1" id="c6e367d4-759f-471d-b13b-d9cdf6ad6cdd" method="GET"><con:settings/><con:parameters/><con:representation type="RESPONSE"><con:mediaType>application/json</con:mediaType><con:status>200</con:status><con:params/></con:representation><con:request name="Request 1" id="34dcb261-5ab7-48e6-ac7e-100ea8d8d117" mediaType="application/json"><con:settings/><con:endpoint>http://debian-vbox/nettbank/public/</con:endpoint><con:request/><con:credentials><con:authType>No Authorization</con:authType></con:credentials><con:jmsConfig JMSDeliveryMode="PERSISTENT"/><con:jmsPropertyConfig/><con:parameters/></con:request></con:method></con:resource></con:interface><con:testSuite id="093a7583-81dd-4f80-8495-70a1138fa4c3" name="TestSuite 1"><con:settings/><con:runType>SEQUENTIAL</con:runType><con:testCase id="55ea80da-da02-436e-b0ea-285c161f5cab" failOnError="true" failTestCaseOnErrors="true" keepSession="true" maxResults="0" name="TestCase 1" searchProperties="true" timeout="0" wsrmEnabled="false" wsrmVersion="1.0" wsrmAckTo="" amfAuthorisation="false" amfEndpoint="" amfLogin="" amfPassword=""><con:settings/><con:testStep type="restrequest" name="Pålogging" id="caec252e-ed81-4434-b824-d785daab37a9"><con:settings/><con:config service="http://debian-vbox" resourcePath="/API/loggInnAdmin.php" methodName="" xsi:type="con:RestRequestStep" xmlns:xsi="http://www.w3.org/2001/XMLSchema-instance"><con:restRequest name="Pålogging" id="4d77e73e-2481-41ec-b1f1-26e99fb36bbd" mediaType="application/json"><con:settings><con:setting id="com.eviware.soapui.impl.wsdl.WsdlRequest@request-headers">&lt;xml-fragment/></con:setting></con:settings><con:endpoint>http://dev.bankidapp.xyz/</con:endpoint><con:request/><con:originalUri>http://debian-vbox/nettbank/public/API/hentAlleKunder.php</con:originalUri><con:assertion type="Valid HTTP Status Codes" id="8f7617d8-c285-4daf-8aee-2cedb893a093" name="Valid HTTP Status Codes"><con:configuration><codes>200</codes></con:configuration></con:assertion><con:assertion type="Simple Contains" id="bb0f2281-b0a8-4a6a-8d0a-418f41f6b6af" name="Contains"><con:configuration><token>"Admin"</token><ignoreCase>false</ignoreCase><useRegEx>false</useRegEx></con:configuration></con:assertion><con:credentials><con:authType>No Authorization</con:authType></con:credentials><con:jmsConfig JMSDeliveryMode="PERSISTENT"/><con:jmsPropertyConfig/><con:parameters>
  <con:entry key="passord" value="Admin"/>
  <con:entry key="bruker" value="Admin"/>
</con:parameters><con:parameterOrder><con:entry>bruker</con:entry><con:entry>passord</con:entry></con:parameterOrder></con:restRequest></con:config></con:testStep><con:testStep type="restrequest" name="HentAlleKunder" id="d7e56d81-05bc-4589-86d1-9822a56c2c0b"><con:settings/><con:config service="http://debian-vbox" resourcePath="/API/hentAlleKunder.php" methodName="Method 1" xsi:type="con:RestRequestStep" xmlns:xsi="http://www.w3.org/2001/XMLSchema-instance"><con:restRequest name="HentAlleKunder" id="34dcb261-5ab7-48e6-ac7e-100ea8d8d117" mediaType="application/json"><con:settings><con:setting id="com.eviware.soapui.impl.wsdl.WsdlRequest@request-headers">&lt;xml-fragment/></con:setting></con:settings><con:endpoint>http://dev.bankidapp.xyz/</con:endpoint><con:request/><con:originalUri>http://dev.bankidapp.xyz/nettbank/public/API/hentAlleKunder.php</con:originalUri><con:assertion type="Simple Contains" id="67cfed23-d025-4865-bf01-c35bb08d1d9a" name="Kunde1"><con:configuration><token>{"Personnummer":"01010110523","Fornavn":"Lene","Etternavn":"Jensen","Adresse":"Askerveien 22","Postnr":"3270","Telefonnr":"22224444","Passord":"Hei","Poststed":"Asker"}</token><ignoreCase>false</ignoreCase><useRegEx>false</useRegEx></con:configuration></con:assertion><con:assertion type="Valid HTTP Status Codes" id="c583b50f-3094-45b9-88c7-16ed090b9ede" name="Valid HTTP Status Codes"><con:configuration><codes>200</codes></con:configuration></con:assertion><con:credentials><con:authType>No Authorization</con:authType></con:credentials><con:jmsConfig JMSDeliveryMode="PERSISTENT"/><con:jmsPropertyConfig/><con:parameters/></con:restRequest></con:config></con:testStep><con:properties/></con:testCase><con:properties/></con:testSuite><con:properties/><con:wssContainer/><con:oAuth2ProfileContainer/><con:sensitiveInformation/></con:soapui-project>